configuru
