Metadata-Version: 1.2
Name: configuru
Version: 0.1.2
Summary: Base class for project configuration with support of env and dotenv
Home-page: https://github.com/pawnhearts/configuru
Author: robotnaoborot
Author-email: robotnaoborot@gmail.com
License: BSD license
Keywords: configuru
Platform: UNKNOWN
Classifier: Development Status :: 2 - Pre-Alpha
Classifier: Intended Audience :: Developers
Classifier: License :: OSI Approved :: BSD License
Classifier: Natural Language :: English
Classifier: Programming Language :: Python :: 3
Classifier: Programming Language :: Python :: 3.5
Classifier: Programming Language :: Python :: 3.6
Classifier: Programming Language :: Python :: 3.7
Classifier: Programming Language :: Python :: 3.8
Requires-Python: >=3.5
